raw2clean
