Metadata-Version: 1.0
Name: raw2clean
Version: 1.0.8
Summary: QC for rawdata without adapter
Home-page: https://github.com/yodeng/raw2clean
Author: Yong Deng
Author-email: yodeng@tju.edu.cn
License: MIT
Platform: UNKNOWN
